tap_jira/__init__.py
tap_jira/client.py
tap_jira/discover.py
tap_jira/streams.py
tap_jira/sync.py
tap_jira/utils.py
tap_jira/schemas/boards.json
tap_jira/schemas/epics.json
tap_jira/schemas/issue_board.json
tap_jira/schemas/issue_changelogs.json
tap_jira/schemas/issue_comments.json
tap_jira/schemas/issue_transitions.json
tap_jira/schemas/issues.json
tap_jira/schemas/project_board.json
tap_jira/schemas/project_categories.json
tap_jira/schemas/project_types.json
tap_jira/schemas/projects.json
tap_jira/schemas/resolutions.json
tap_jira/schemas/roles.json
tap_jira/schemas/sprints.json
tap_jira/schemas/users.json
tap_jira/schemas/versions.json
tap_jira/schemas/worklogs.json
ps_tap_jira-3.0.0.dist-info/LICENSE
ps_tap_jira-3.0.0.dist-info/METADATA
ps_tap_jira-3.0.0.dist-info/WHEEL
ps_tap_jira-3.0.0.dist-info/entry_points.txt
ps_tap_jira-3.0.0.dist-info/top_level.txt
ps_tap_jira-3.0.0.dist-info/RECORD
