Metadata-Version: 2.1
Name: ps-tap-jira
Version: 3.0.0
Summary: Singer.io tap for extracting data from the Jira API
Home-page: http://singer.io
Author: Stitch
License: UNKNOWN
Download-URL: https://github.com/saianil58/ps_tap_jira/archive/refs/tags/3.1.tar.gz
Platform: UNKNOWN
Classifier: Programming Language :: Python :: 3 :: Only
License-File: LICENSE
Requires-Dist: singer-python (==5.9.0)
Requires-Dist: requests (==2.20.0)
Provides-Extra: dev
Requires-Dist: pylint ; extra == 'dev'
Requires-Dist: nose ; extra == 'dev'
Requires-Dist: ipdb ; extra == 'dev'
